sospex/__init__.py
sospex/apertures.py
sospex/cloud.py
sospex/copyright.txt
sospex/graphics.py
sospex/interactors.py
sospex/lines.py
sospex/mainwindow.py
sospex/moments.py
sospex/specobj.py
sospex/start.py
sospex/yellow-stylesheet.css
sospex/help/Help.html
sospex/help/apertures.html
sospex/help/blink.html
sospex/help/contours.html
sospex/help/croptrim.html
sospex/help/erase.html
sospex/help/extimages.html
sospex/help/intensity.html
sospex/help/moments.html
sospex/help/save.html
sospex/help/slice.html
sospex/help/slider.html
sospex/help/specpanel.html
sospex/help/start.html
sospex/help/tutorials.html
sospex/help/zoom.html
sospex/icons/afmhot.png
sospex/icons/apertures.png
sospex/icons/black.png
sospex/icons/blink.png
sospex/icons/blue.png
sospex/icons/camera.png
sospex/icons/check.png
sospex/icons/circle.png
sospex/icons/cloud.png
sospex/icons/computeMoments.png
sospex/icons/continuum.png
sospex/icons/contours.png
sospex/icons/crop.png
sospex/icons/cut.png
sospex/icons/cyan.png
sospex/icons/dispersion.png
sospex/icons/download.png
sospex/icons/ds9a.png
sospex/icons/ds9aips0.png
sospex/icons/ds9b.png
sospex/icons/ds9cool.png
sospex/icons/ds9he.png
sospex/icons/ds9heat.png
sospex/icons/ds9i8.png
sospex/icons/ds9rainbow.png
sospex/icons/ellipse.png
sospex/icons/eraser.png
sospex/icons/exit.png
sospex/icons/fitCont.png
sospex/icons/fitregion.png
sospex/icons/gaussfit.png
sospex/icons/gist_earth.png
sospex/icons/gist_gray.png
sospex/icons/gist_heat.png
sospex/icons/guess.png
sospex/icons/guessCont.png
sospex/icons/help.png
sospex/icons/home_large.png
sospex/icons/hresize.png
sospex/icons/inferno.png
sospex/icons/issue.png
sospex/icons/jet.png
sospex/icons/levels.png
sospex/icons/lime.png
sospex/icons/list.png
sospex/icons/location.png
sospex/icons/magenta.png
sospex/icons/map.png
sospex/icons/mask.png
sospex/icons/move_large.png
sospex/icons/new.png
sospex/icons/next.png
sospex/icons/niet.png
sospex/icons/ocean.png
sospex/icons/open.png
sospex/icons/plasma.png
sospex-0.33b0.dist-info/LICENSE
sospex-0.33b0.dist-info/METADATA
sospex-0.33b0.dist-info/WHEEL
sospex-0.33b0.dist-info/top_level.txt
sospex-0.33b0.dist-info/RECORD
